LICENSE.txt
MANIFEST.in
README.txt
setup.py
lfs_solr/__init__.py
lfs_solr/listeners.py
lfs_solr/settings.py
lfs_solr/urls.py
lfs_solr/utils.py
lfs_solr/views.py
lfs_solr.egg-info/PKG-INFO
lfs_solr.egg-info/SOURCES.txt
lfs_solr.egg-info/dependency_links.txt
lfs_solr.egg-info/not-zip-safe
lfs_solr.egg-info/requires.txt
lfs_solr.egg-info/top_level.txt
lfs_solr/conf/schema.xml
lfs_solr/templates/lfs_solr/livesearch_results.html
lfs_solr/templates/lfs_solr/search_results.html