Metadata-Version: 1.0
Name: lfs-solr
Version: 1.0b1
Summary: Solr integration for LFC
Home-page: http://www.iqpp.de
Author: Kai Diefenbach
Author-email: kai.diefenbach@iqpp.de
License: BSD
Keywords: django lfs search solr
Platform: UNKNOWN
Classifier: Development Status :: 4 - Beta
Classifier: Environment :: Web Environment
Classifier: Framework :: Django
Classifier: License :: OSI Approved :: BSD License
Classifier: Operating System :: OS Independent
Classifier: Programming Language :: Python
